klai/__init__.py
klai/client.py
klai/config.py
klai/db.py
klai/main.py
klai/templates/index.html
klai/web.py
klai-1.0.0.dist-info/METADATA
klai-1.0.0.dist-info/WHEEL
klai-1.0.0.dist-info/entry_points.txt
klai-1.0.0.dist-info/RECORD
